MANIFEST.in
README.txt
setup.cfg
setup.py
zopyx.plone.cassandra-configure.zcml
docs/HISTORY.txt
docs/INSTALL.txt
docs/LICENSE.GPL
docs/LICENSE.txt
zopyx/__init__.py
zopyx.plone.cassandra.egg-info/PKG-INFO
zopyx.plone.cassandra.egg-info/SOURCES.txt
zopyx.plone.cassandra.egg-info/dependency_links.txt
zopyx.plone.cassandra.egg-info/entry_points.txt
zopyx.plone.cassandra.egg-info/namespace_packages.txt
zopyx.plone.cassandra.egg-info/not-zip-safe
zopyx.plone.cassandra.egg-info/requires.txt
zopyx.plone.cassandra.egg-info/top_level.txt
zopyx/plone/__init__.py
zopyx/plone/cassandra/__init__.py
zopyx/plone/cassandra/cassandra.pt
zopyx/plone/cassandra/cassandra.py
zopyx/plone/cassandra/configure.zcml
zopyx/plone/cassandra/profiles.zcml
zopyx/plone/cassandra/setuphandlers.py
zopyx/plone/cassandra/skins.zcml
zopyx/plone/cassandra/tests.py
zopyx/plone/cassandra/version.txt
zopyx/plone/cassandra/profiles/default/import_steps.xml
zopyx/plone/cassandra/profiles/default/skins.xml
zopyx/plone/cassandra/profiles/default/zopyx.plone.cassandra_various.txt
zopyx/plone/cassandra/skins/zopyx_plone_cassandra_templates/CONTENT.txt
zopyx/plone/cassandra/skins/zopyx_plone_cassandra_templates/computeRoleMap.py