Metadata-Version: 1.0
Name: zopyx.plone.cassandra
Version: 0.3.4
Summary: Show all assigned local roles within a subtree for any Plone 4 site
Home-page: http://svn.plone.org/svn/collective/
Author: Andreas Jung
Author-email: info@zopyx.com
License: ZPL
Keywords: web zope plone theme
Platform: UNKNOWN
Classifier: Framework :: Plone
Classifier: Framework :: Plone :: 4.0
Classifier: Framework :: Plone :: 4.1
Classifier: Framework :: Plone :: 4.2
Classifier: Programming Language :: Python
Classifier: Topic :: Software Development :: Libraries :: Python Modules
